reasoners/__init__.py
reasoners-0.1.0.dist-info/LICENSE
reasoners-0.1.0.dist-info/METADATA
reasoners-0.1.0.dist-info/WHEEL
reasoners-0.1.0.dist-info/RECORD
